ferrit.py
ferrit-0.0.12.dist-info/LICENSE.md
ferrit-0.0.12.dist-info/METADATA
ferrit-0.0.12.dist-info/WHEEL
ferrit-0.0.12.dist-info/entry_points.txt
ferrit-0.0.12.dist-info/top_level.txt
ferrit-0.0.12.dist-info/zip-safe
ferrit-0.0.12.dist-info/RECORD
