Metadata-Version: 2.1
Name: ferrit
Version: 0.0.12
Summary: A stupid tool for listing and checking out Gerrit changes
Home-page: https://github.com/erikmansson/ferrit
Author: Erik Månsson
Author-email: erik@mansson.xyz
License: UNKNOWN
Platform: UNKNOWN
Classifier: Programming Language :: Python :: 3
Classifier: License :: OSI Approved :: MIT License
Classifier: Operating System :: OS Independent
Requires-Python: >=3.5
Requires-Dist: requests
Requires-Dist: requests-futures
